unicef_vision/__init__.py
unicef_vision/admin.py
unicef_vision/client.py
unicef_vision/exceptions.py
unicef_vision/loaders.py
unicef_vision/models.py
unicef_vision/settings.py
unicef_vision/synchronizers.py
unicef_vision/utils.py
unicef_vision/vision/__init__.py
unicef_vision/vision/admin.py
unicef_vision/vision/models.py
unicef_vision/vision/migrations/0001_initial.py
unicef_vision/vision/migrations/__init__.py
unicef_vision-0.6.dist-info/LICENSE
unicef_vision-0.6.dist-info/METADATA
unicef_vision-0.6.dist-info/WHEEL
unicef_vision-0.6.dist-info/top_level.txt
unicef_vision-0.6.dist-info/RECORD
