Metadata-Version: 2.1
Name: unicef-vision
Version: 0.6
Summary: UNKNOWN
Home-page: https://github.com/unicef/unicef-vision
Author: UNICEF
Author-email: rapidpro@unicef.org
License: Apache 2 License
Platform: any
Classifier: Environment :: Web Environment
Classifier: Framework :: Django
Classifier: License :: OSI Approved :: MIT License
Classifier: Programming Language :: Python
Classifier: Programming Language :: Python :: 3
Classifier: Programming Language :: Python :: 3.7
Classifier: Programming Language :: Python :: 3.8
Classifier: Framework :: Django
Classifier: Framework :: Django :: 2.2
Classifier: Framework :: Django :: 3.0
Classifier: Framework :: Django :: 3.1
Requires-Dist: Django
Requires-Dist: requests
Provides-Extra: test
Requires-Dist: responses ; extra == 'test'
Requires-Dist: mock ; extra == 'test'
Requires-Dist: factory-boy ; extra == 'test'
Requires-Dist: pytest ; extra == 'test'
Requires-Dist: pytest-pythonpath ; extra == 'test'
Requires-Dist: pytest-cov ; extra == 'test'
Requires-Dist: pytest-django ; extra == 'test'
Requires-Dist: pytest-echo ; extra == 'test'
Requires-Dist: isort ; extra == 'test'
Requires-Dist: flake8 ; extra == 'test'
